autopress/__init__.py
autopress/autopress.py
autopress/openai.py
autopress/utils.py
autopress/cli/__init__.py
autopress/cli/__main__.py
autopress/cli/configure.py
autopress/settings/__init__.py
autopress-0.1.0.dist-info/METADATA
autopress-0.1.0.dist-info/WHEEL
autopress-0.1.0.dist-info/entry_points.txt
autopress-0.1.0.dist-info/top_level.txt
autopress-0.1.0.dist-info/RECORD
