Metadata-Version: 2.1
Name: autopress
Version: 0.1.0
Author: Edward Laurence
Requires-Dist: openai
Requires-Dist: python-dotenv
Requires-Dist: clisync
